django_serfilter/__init__.py
django_serfilter/base.py
django_serfilter-0.1.1.dist-info/LICENSE.md
django_serfilter-0.1.1.dist-info/METADATA
django_serfilter-0.1.1.dist-info/WHEEL
django_serfilter-0.1.1.dist-info/top_level.txt
django_serfilter-0.1.1.dist-info/RECORD
