Metadata-Version: 2.1
Name: django-serfilter
Version: 0.1.1
Summary: Easy to use, highly customizable filter backend for Django Rest Framework
Home-page: https://github.com/Raekkeri/django-serfilter
Author: Teemu Husso
Author-email: teemu.husso@gmail.com
License: UNKNOWN
Keywords: django,filter,backend,serializer
Platform: UNKNOWN
Requires-Dist: Django (<3.0,>=1.11)
Requires-Dist: djangorestframework (<4.0,>=3.0)
Requires-Dist: setuptools
